miarec_sshfs/__init__.py
miarec_sshfs/_version.txt
miarec_sshfs/error_tools.py
miarec_sshfs/file.py
miarec_sshfs/opener.py
miarec_sshfs/sshfs.py
miarec_sshfs-2024.1.5.dist-info/COPYING
miarec_sshfs-2024.1.5.dist-info/METADATA
miarec_sshfs-2024.1.5.dist-info/WHEEL
miarec_sshfs-2024.1.5.dist-info/entry_points.txt
miarec_sshfs-2024.1.5.dist-info/top_level.txt
miarec_sshfs-2024.1.5.dist-info/zip-safe
miarec_sshfs-2024.1.5.dist-info/RECORD
