Metadata-Version: 2.1
Name: miarec_sshfs
Version: 2024.1.5
Summary: Pyfilesystem2 over SSH using paramiko
Home-page: https://github.com/miarec/miarec_sshfs
Author: MiaRec
Author-email: support@miarec.com
License: LGPLv2+
Project-URL: Bug Tracker, https://github.com/miarec/miarec_sshfs/issues
Project-URL: Builds, https://github.com/miarec/miarec_sshfs/actions
Keywords: filesystem,Pyfilesystem2,ssh,sftp,paramiko
Platform: any
Classifier: Development Status :: 5 - Production/Stable
Classifier: Intended Audience :: Developers
Classifier: License :: OSI Approved :: GNU Lesser General Public License v2 or later (LGPLv2+)
Classifier: Operating System :: OS Independent
Classifier: Programming Language :: Python
Classifier: Programming Language :: Python :: 2.7
Classifier: Programming Language :: Python :: 3.5
Classifier: Programming Language :: Python :: 3.6
Classifier: Programming Language :: Python :: 3.7
Classifier: Programming Language :: Python :: 3.8
Classifier: Programming Language :: Python :: 3.9
Classifier: Programming Language :: Python :: 3.10
Classifier: Programming Language :: Python :: 3.11
Classifier: Topic :: Internet
Classifier: Topic :: Security
Classifier: Topic :: Software Development :: Libraries :: Python Modules
Classifier: Topic :: System :: Filesystems
Requires-Python: >=3.6
License-File: COPYING
Requires-Dist: property-cached ~=1.6
Requires-Dist: fs ~=2.2
Requires-Dist: paramiko <4.0,>=2.0
Requires-Dist: six ~=1.10
Requires-Dist: setuptools >=38.3.0
Requires-Dist: configparser ~=3.2 ; python_version < "3"
Provides-Extra: test
Requires-Dist: pytest ~=7.4 ; extra == 'test'
Requires-Dist: pytest-cov ~=4.1 ; extra == 'test'
Requires-Dist: docker ~=6.0 ; extra == 'test'
Requires-Dist: semantic-version ~=2.6 ; extra == 'test'
